nickspylib/__init__.py
nickspylib/random.py
nickspylib-0.1.4.dist-info/METADATA
nickspylib-0.1.4.dist-info/WHEEL
nickspylib-0.1.4.dist-info/RECORD
